{
  "richardDoe": {
    "name": "Richard Doe",
    "avatar": "https://raw.githubusercontent.com/RapidAPI/DevRel-Stack-Data/dev/authors/richard%20doe/avatar.png",
    "designation": "Content Producer @ RapidAPI",
    "isDeveloperProgramMember": false
  },
  "saad": {
    "name": "Saad Irfan",
    "avatar": "https://raw.githubusercontent.com/RapidAPI/DevRel-Stack-Data/dev/authors/saad/avatar.png",
    "designation": "Jr Content Developer (External Contractor)",
    "isDeveloperProgramMember": true
  },
  "pratham": {
    "name": "Pratham",
    "avatar": "https://raw.githubusercontent.com/PrathamKumar14/DevRel-Stack-Data/dev/authors/pratham/avatar.png",
    "designation": "Developer Advocate @ RapidAPI",
    "isDeveloperProgramMember": true
  }
}
